{"seed": {"1": 0, "2": 1, "8": 1}, "dualVariables": [["yu_1_2_8n0", 1.0], ["yu_1_2_8_3n1", 0.75], ["yu_1_2_8_3n4", 0.25], ["yu_1_4_8_3p2", 1.0], ["yu_1_4_8_5n2", 1.0], ["yu_1_6_8_5n1", 0.5], ["yu_1_6_8_5n2", 0.5], ["yu_1_6_8_7n3", -1.1102230246251565e-16], ["yu_1_6_8_7p2", 1.0], ["yu_1_8_7n0", 1.0], ["yu_1_8_2p2", 1.0], ["yu_1_8_2_7n2", 1.0], ["yu_1_6_2_7n4", 1.0], ["yu_1_6_2_5p1", 1.0], ["yu_1_4_2_5n4", 1.0], ["yu_1_4_2_3n3", 0.5], ["yu_1_4_2_3p3", 0.5], ["yu_1_2_3n0", 0.75], ["yu_1_2_3p2", 0.25], ["yu_2_3_4n0", 0.5], ["yu_2_3_4p2", 0.5], ["yu_2_5_3_4n4", 0.25000000000000006], ["yu_2_5_3_4p1", 0.6666666666666667], ["yu_2_5_3_4p3", 0.08333333333333326], ["yu_2_5_3_6n3", 0.5833333333333333], ["yu_2_5_3_6p3", 0.41666666666666674], ["yu_2_7_3_6n2", 0.41666666666666663], ["yu_2_7_3_6p2", 0.5833333333333334], ["yu_2_7_3_8p1", 0.08333333333333337], ["yu_2_7_3_8p2", 0.29166666666666663], ["yu_2_7_3_8p3", 0.625], ["yu_1_3_8_2n1", 1.0], ["yu_1_3_2n0", 0.5], ["yu_1_3_2p2", 0.5], ["yu_2_4_3p2", 0.5], ["yu_2_4_3p3", 0.5], ["yu_1_3_2_4n2", 1.0], ["yu_1_3_8_4n4", 0.08333333333333326], ["yu_1_3_8_4p1", 0.9166666666666667], ["yu_3_8_4_7n2", 0.7916666666666666], ["yu_3_8_4_7p2", 0.20833333333333337], ["yu_3_6_4_7n1", 0.33333333333333337], ["yu_3_6_4_7p1", 0.6666666666666666], ["yu_3_6_4_5n2", 1.0], ["yu_3_4_5p1", 0.6666666666666667], ["yu_3_4_5p2", 0.16666666666666663], ["yu_3_4_5p3", 0.16666666666666663], ["yu_4_5_6n0", 0.8333333333333334], ["yu_4_5_6p3", 0.16666666666666663], ["yu_4_7_5_6n2", 0.6666666666666666], ["yu_4_7_5_6p2", 0.33333333333333337], ["yu_4_7_5_8n2", 0.7083333333333334], ["yu_4_7_5_8p3", 0.29166666666666663], ["yu_1_5_8_4n4", 1.0], ["yu_1_5_2_4n1", 0.5833333333333334], ["yu_1_5_2_4n2", 0.41666666666666663], ["yu_2_4_3_5n1", 0.75], ["yu_2_4_3_5p4", 0.25], ["yu_3_5_4p2", 0.75], ["yu_3_5_4p3", 0.25], ["yu_4_6_5n0", 0.5], ["yu_4_6_5p2", 0.5], ["yu_3_5_4_6n1", 0.25], ["yu_3_5_4_6n2", 0.75], ["yu_2_6_3_5n1", 0.41666666666666674], ["yu_2_6_3_5n4", 0.5833333333333333], ["yu_1_5_2_6n2", 0.08333333333333337], ["yu_1_5_2_6p4", 0.9166666666666666], ["yu_1_5_8_6p1", 1.0], ["yu_5_8_6_7n2", 0.5], ["yu_5_8_6_7p2", 0.33333333333333337], ["yu_5_8_6_7p4", 0.16666666666666663], ["yu_5_6_7p3", 1.0], ["yu_6_7_8n0", 1.0], ["yu_1_7_8_6n1", 0.6666666666666666], ["yu_1_7_8_6p1", 0.33333333333333337], ["yu_1_7_2_6n2", 0.33333333333333337], ["yu_1_7_2_6p2", 0.6666666666666666], ["yu_2_6_3_7n2", 0.5], ["yu_2_6_3_7p1", 0.5], ["yu_3_7_4_6n4", 1.0], ["yu_4_6_5_7p4", 1.0], ["yu_5_7_6p2", 0.5], ["yu_5_7_6p3", 0.5], ["yu_6_8_7n0", 1.0], ["yu_5_7_6_8p1", 1.0], ["yu_4_8_5_7p3", 1.0], ["yu_3_7_4_8p3", 1.0], ["yu_2_8_3_7n1", 0.6666666666666667], ["yu_2_8_3_7n4", 0.3333333333333333], ["yu_1_7_2_8n1", 0.16666666666666669], ["yu_1_7_2_8p1", 0.8333333333333333], ["yu_1_7_8n0", 0.33333333333333337], ["yu_1_7_8p1", 0.6666666666666667], ["yu_1_7_8p3", -1.1102230246251565e-16], ["yu_1_9_2n0", 0.25], ["yu_1_9_2p1", 0.25], ["yu_1_9_2p2", 0.25], ["yu_1_9_2p3", 0.25], ["yu_2_9_3n0", 0.5], ["yu_2_9_3p1", 0.5], ["yu_3_9_4n0", 0.5], ["yu_3_9_4p1", 0.5], ["yu_4_9_5n0", 0.5], ["yu_4_9_5p1", 0.5], ["yu_5_9_6n0", 0.25], ["yu_5_9_6p1", 0.25], ["yu_5_9_6p2", 0.25], ["yu_5_9_6p3", 0.25], ["yu_6_9_7n0", 0.5], ["yu_6_9_7p1", 0.5], ["yu_7_9_8p1", 0.5], ["yu_7_9_8p2", 0.5], ["yu_1_8_9n0", 0.5], ["yu_1_8_9p2", 0.5]], "treeWidths": {"0": 1, "1": 2, "2": 1, "3": 1, "4": 1, "5": 2, "6": 2, "7": 3, "8": 3, "9": 4, "10": 4, "11": 3, "12": 4, "13": 4, "14": 3, "15": 4}, "nuOmega": 19, "root": {"seed": {"1": 0, "2": 1, "8": 1}, "partition": {"1": 0, "2": 1, "8": 1}, "isValid": true, "id": 1, "leftC": {"seed": {"1": 0, "2": 1, "8": 1}, "partition": {"1": 0, "2": 1, "8": 1}, "isValid": false, "id": 2, "leftC": null, "rightC": null, "system": ["xa_1_2 + xa_1_8 + xa_2_8 - 2"], "sumOmega": 0, "ni": 1, "pathFromRoot": ["yu_1_2_8n0"]}, "rightC": {"seed": {"1": 0, "2": 1, "8": 1}, "partition": {"1": 0, "2": 1, "8": 1}, "isValid": true, "id": 3, "leftC": {"seed": {"1": 0, "2": 1, "8": 1}, "partition": {"1": 0, "2": 1, "8": 1}, "isValid": true, "id": 6, "leftC": {"seed": {"1": 0, "2": 1, "8": 1}, "partition": {"1": 0, "2": 1, "8": 1, "3": 1}, "isValid": true, "id": 12, "leftC": {"seed": {"1": 0, "2": 1, "8": 1}, "partition": {"1": 0, "2": 1, "8": 1, "3": 1, "4": 1}, "isValid": true, "id": 24, "leftC": {"seed": {"1": 0, "2": 1, "8": 1}, "partition": {"1": 0, "2": 1, "8": 1, "3": 1, "4": 1}, "isValid": false, "id": 48, "leftC": null, "rightC": null, "system": ["xa_1_4 + xa_1_5 - xa_4_8 + xa_5_8 - 2"], "sumOmega": 4.0, "ni": 4, "pathFromRoot": ["yu_1_2_8n0", "yu_1_2_8_3n1", "yu_1_2_8_3n4", "yu_1_4_8_3p2", "yu_1_4_8_5n2"]}, "rightC": {"seed": {"1": 0, "2": 1, "8": 1}, "partition": {"1": 0, "2": 1, "8": 1, "3": 1, "4": 1}, "isValid": true, "id": 49, "leftC": {"seed": {"1": 0, "2": 1, "8": 1}, "partition": {"1": 0, "2": 1, "8": 1, "3": 1, "4": 1, "6": 1}, "isValid": true, "id": 98, "leftC": {"seed": {"1": 0, "2": 1, "8": 1}, "partition": {"1": 0, "2": 1, "8": 1, "3": 1, "4": 1, "6": 1}, "isValid": false, "id": 196, "leftC": null, "rightC": null, "system": ["xa_1_5 + xa_1_6 + xa_5_8 - xa_6_8 - 2"], "sumOmega": 4.0, "ni": 7, "pathFromRoot": ["yu_1_2_8n0", "yu_1_2_8_3n1", "yu_1_2_8_3n4", "yu_1_4_8_3p2", "yu_1_4_8_5n2", "yu_1_6_8_5n1", "yu_1_6_8_5n2"]}, "rightC": {"seed": {"1": 0, "2": 1, "8": 1}, "partition": {"1": 0, "2": 1, "8": 1, "3": 1, "4": 1, "6": 1}, "isValid": true, "id": 197, "leftC": {"seed": {"1": 0, "2": 1, "8": 1}, "partition": {"1": 0, "2": 1, "8": 1, "3": 1, "4": 1, "6": 1, "7": 0}, "isValid": true, "id": 394, "leftC": {"seed": {"1": 0, "2": 1, "8": 1}, "partition": {"1": 0, "2": 1, "8": 1, "3": 1, "4": 1, "6": 1, "7": 0}, "isValid": true, "id": 788, "leftC": {"seed": {"1": 0, "2": 1, "8": 1}, "partition": {"1": 0, "2": 1, "8": 1, "3": 1, "4": 1, "6": 1, "7": 0}, "isValid": false, "id": 1576, "leftC": null, "rightC": null, "system": ["xa_1_7 + xa_1_8 + xa_7_8 - 2"], "sumOmega": 6.0, "ni": 8, "pathFromRoot": ["yu_1_2_8n0", "yu_1_2_8_3n1", "yu_1_2_8_3n4", "yu_1_4_8_3p2", "yu_1_4_8_5n2", "yu_1_6_8_5n1", "yu_1_6_8_5n2", "yu_1_6_8_7n3", "yu_1_6_8_7p2", "yu_1_8_7n0"]}, "rightC": {"seed": {"1": 0, "2": 1, "8": 1}, "partition": {"1": 0, "2": 1, "8": 1, "3": 1, "4": 1, "6": 1, "7": 0}, "isValid": true, "id": 1577, "leftC": {"seed": {"1": 0, "2": 1, "8": 1}, "partition": {"1": 0, "2": 1, "8": 1, "3": 1, "4": 1, "6": 1, "7": 0}, "isValid": true, "id": 3154, "leftC": {"seed": {"1": 0, "2": 1, "8": 1}, "partition": {"1": 0, "2": 1, "8": 1, "3": 1, "4": 1, "6": 1, "7": 0}, "isValid": false, "id": 6308, "leftC": null, "rightC": null, "system": ["xa_1_7 + xa_1_8 + xa_2_7 - xa_2_8 - 2"], "sumOmega": 8.0, "ni": 8, "pathFromRoot": ["yu_1_2_8n0", "yu_1_2_8_3n1", "yu_1_2_8_3n4", "yu_1_4_8_3p2", "yu_1_4_8_5n2", "yu_1_6_8_5n1", "yu_1_6_8_5n2", "yu_1_6_8_7n3", "yu_1_6_8_7p2", "yu_1_8_7n0", "yu_1_8_2p2", "yu_1_8_2_7n2"]}, "rightC": {"seed": {"1": 0, "2": 1, "8": 1}, "partition": {"1": 0, "2": 1, "8": 1, "3": 1, "4": 1, "6": 1, "7": 0}, "isValid": true, "id": 6309, "leftC": {"seed": {"1": 0, "2": 1, "8": 1}, "partition": {"1": 0, "2": 1, "8": 1, "3": 1, "4": 1, "6": 1, "7": 0}, "isValid": false, "id": 12618, "leftC": null, "rightC": null, "system": ["xa_1_6 - xa_1_7 + xa_2_6 + xa_2_7 - 2"], "sumOmega": 8.0, "ni": 8, "pathFromRoot": ["yu_1_2_8n0", "yu_1_2_8_3n1", "yu_1_2_8_3n4", "yu_1_4_8_3p2", "yu_1_4_8_5n2", "yu_1_6_8_5n1", "yu_1_6_8_5n2", "yu_1_6_8_7n3", "yu_1_6_8_7p2", "yu_1_8_7n0", "yu_1_8_2p2", "yu_1_8_2_7n2", "yu_1_6_2_7n4"]}, "rightC": {"seed": {"1": 0, "2": 1, "8": 1}, "partition": {"1": 0, "2": 1, "8": 1, "3": 1, "4": 1, "6": 1, "7": 0}, "isValid": true, "id": 12619, "leftC": {"seed": {"1": 0, "2": 1, "8": 1}, "partition": {"1": 0, "2": 1, "8": 1, "3": 1, "4": 1, "6": 1, "7": 0}, "isValid": false, "id": 25238, "leftC": null, "rightC": null, "system": ["-xa_1_5 + xa_1_6 - xa_2_5 - xa_2_6"], "sumOmega": 8.0, "ni": 8, "pathFromRoot": ["yu_1_2_8n0", "yu_1_2_8_3n1", "yu_1_2_8_3n4", "yu_1_4_8_3p2", "yu_1_4_8_5n2", "yu_1_6_8_5n1", "yu_1_6_8_5n2", "yu_1_6_8_7n3", "yu_1_6_8_7p2", "yu_1_8_7n0", "yu_1_8_2p2", "yu_1_8_2_7n2", "yu_1_6_2_7n4", "yu_1_6_2_5p1"]}, "rightC": {"seed": {"1": 0, "2": 1, "8": 1}, "partition": {"1": 0, "2": 1, "8": 1, "3": 1, "4": 1, "6": 1, "7": 0}, "isValid": true, "id": 25239, "leftC": {"seed": {"1": 0, "2": 1, "8": 1}, "partition": {"1": 0, "2": 1, "8": 1, "3": 1, "4": 1, "6": 1, "7": 0, "5": 1}, "isValid": true, "id": 50478, "leftC": null, "rightC": null, "system": ["Eq(xa_1_2, 1)", "Eq(xa_2_7, 1)", "Eq(xa_1_3, 1)", "Eq(xa_2_6, 0)", "Eq(xa_6_8, 0)", "Eq(xa_4_8, 0)", "Eq(xa_2_8, 0)", "Eq(xa_1_4, 1)", "Eq(xa_3_8, 0)", "Eq(xa_1_8, 1)", "Eq(xa_1_6, 1)", "Eq(xa_1_7, 0)", "Eq(xa_7_8, 1)", "Eq(xa_2_5, xa_5_8)", "Eq(xa_1_5, 1 - xa_5_8)", "xa_1_4 - xa_1_5 + xa_2_4 + xa_2_5", "xa_1_4 - xa_1_5 + xa_2_4 + xa_2_5 - 2"], "sumOmega": 11.0, "ni": 12, "pathFromRoot": ["yu_1_2_8n0", "yu_1_2_8_3n1", "yu_1_2_8_3n4", "yu_1_4_8_3p2", "yu_1_4_8_5n2", "yu_1_6_8_5n1", "yu_1_6_8_5n2", "yu_1_6_8_7n3", "yu_1_6_8_7p2", "yu_1_8_7n0", "yu_1_8_2p2", "yu_1_8_2_7n2", "yu_1_6_2_7n4", "yu_1_6_2_5p1", "yu_1_4_2_5n4"]}, "rightC": {"seed": {"1": 0, "2": 1, "8": 1}, "partition": {"1": 0, "2": 1, "8": 1, "3": 1, "4": 1, "6": 1, "7": 0, "5": 0}, "isValid": true, "id": 50479, "leftC": null, "rightC": null, "system": ["Eq(xa_1_2, 1)", "Eq(xa_2_7, 1)", "Eq(xa_1_3, 1)", "Eq(xa_2_6, 0)", "Eq(xa_6_8, 0)", "Eq(xa_4_8, 0)", "Eq(xa_2_8, 0)", "Eq(xa_1_4, 1)", "Eq(xa_3_8, 0)", "Eq(xa_1_8, 1)", "Eq(xa_1_6, 1)", "Eq(xa_1_7, 0)", "Eq(xa_7_8, 1)", "Eq(xa_2_5, xa_5_8)", "Eq(xa_1_5, 1 - xa_5_8)", "xa_1_4 - xa_1_5 + xa_2_4 + xa_2_5 - 2", "-xa_1_2 - xa_1_8 + xa_2_8"], "sumOmega": 9.0, "ni": 9, "pathFromRoot": ["yu_1_2_8n0", "yu_1_2_8_3n1", "yu_1_2_8_3n4", "yu_1_4_8_3p2", "yu_1_4_8_5n2", "yu_1_6_8_5n1", "yu_1_6_8_5n2", "yu_1_6_8_7n3", "yu_1_6_8_7p2", "yu_1_8_7n0", "yu_1_8_2p2", "yu_1_8_2_7n2", "yu_1_6_2_7n4", "yu_1_6_2_5p1", "yu_1_4_2_5n4"]}, "system": ["Eq(xa_1_2, 1)", "Eq(xa_2_7, 1)", "Eq(xa_1_3, 1)", "Eq(xa_2_6, 0)", "Eq(xa_6_8, 0)", "Eq(xa_4_8, 0)", "Eq(xa_2_8, 0)", "Eq(xa_1_4, 1)", "Eq(xa_3_8, 0)", "Eq(xa_1_8, 1)", "Eq(xa_1_6, 1)", "Eq(xa_1_7, 0)", "Eq(xa_7_8, 1)", "Eq(xa_2_5, xa_5_8)", "Eq(xa_1_5, 1 - xa_5_8)"], "sumOmega": 8.0, "ni": 8, "pathFromRoot": ["yu_1_2_8n0", "yu_1_2_8_3n1", "yu_1_2_8_3n4", "yu_1_4_8_3p2", "yu_1_4_8_5n2", "yu_1_6_8_5n1", "yu_1_6_8_5n2", "yu_1_6_8_7n3", "yu_1_6_8_7p2", "yu_1_8_7n0", "yu_1_8_2p2", "yu_1_8_2_7n2", "yu_1_6_2_7n4", "yu_1_6_2_5p1"]}, "system": ["Eq(xa_1_2, 1)", "Eq(xa_2_7, 1)", "Eq(xa_1_3, 1)", "Eq(xa_2_6, 0)", "Eq(xa_6_8, 0)", "Eq(xa_4_8, 0)", "Eq(xa_2_8, 0)", "Eq(xa_1_4, 1)", "Eq(xa_3_8, 0)", "Eq(xa_1_8, 1)", "Eq(xa_1_6, 1)", "Eq(xa_1_7, 0)", "Eq(xa_7_8, 1)", "Eq(xa_1_5, 1 - xa_5_8)"], "sumOmega": 8.0, "ni": 8, "pathFromRoot": ["yu_1_2_8n0", "yu_1_2_8_3n1", "yu_1_2_8_3n4", "yu_1_4_8_3p2", "yu_1_4_8_5n2", "yu_1_6_8_5n1", "yu_1_6_8_5n2", "yu_1_6_8_7n3", "yu_1_6_8_7p2", "yu_1_8_7n0", "yu_1_8_2p2", "yu_1_8_2_7n2", "yu_1_6_2_7n4"]}, "system": ["Eq(xa_1_2, 1)", "Eq(xa_2_7, 1)", "Eq(xa_1_3, 1)", "Eq(xa_6_8, 0)", "Eq(xa_4_8, 0)", "Eq(xa_2_8, 0)", "Eq(xa_1_4, 1)", "Eq(xa_3_8, 0)", "Eq(xa_1_8, 1)", "Eq(xa_1_6, 1)", "Eq(xa_1_7, 0)", "Eq(xa_7_8, 1)", "Eq(xa_1_5, 1 - xa_5_8)"], "sumOmega": 8.0, "ni": 8, "pathFromRoot": ["yu_1_2_8n0", "yu_1_2_8_3n1", "yu_1_2_8_3n4", "yu_1_4_8_3p2", "yu_1_4_8_5n2", "yu_1_6_8_5n1", "yu_1_6_8_5n2", "yu_1_6_8_7n3", "yu_1_6_8_7p2", "yu_1_8_7n0", "yu_1_8_2p2", "yu_1_8_2_7n2"]}, "system": ["Eq(xa_1_2, 1)", "Eq(xa_1_3, 1)", "Eq(xa_6_8, 0)", "Eq(xa_4_8, 0)", "Eq(xa_2_8, 0)", "Eq(xa_1_4, 1)", "Eq(xa_3_8, 0)", "Eq(xa_1_8, 1)", "Eq(xa_1_6, 1)", "Eq(xa_1_7, 0)", "Eq(xa_7_8, 1)", "Eq(xa_1_5, 1 - xa_5_8)"], "sumOmega": 8.0, "ni": 8, "pathFromRoot": ["yu_1_2_8n0", "yu_1_2_8_3n1", "yu_1_2_8_3n4", "yu_1_4_8_3p2", "yu_1_4_8_5n2", "yu_1_6_8_5n1", "yu_1_6_8_5n2", "yu_1_6_8_7n3", "yu_1_6_8_7p2", "yu_1_8_7n0", "yu_1_8_2p2"]}, "rightC": {"seed": {"1": 0, "2": 1, "8": 1}, "partition": {"1": 0, "2": 1, "8": 1, "3": 1, "4": 1, "6": 1, "7": 0}, "isValid": false, "id": 3155, "leftC": null, "rightC": null, "system": ["-xa_1_6 - xa_1_7 + xa_6_8 - xa_7_8"], "sumOmega": 8.0, "ni": 8, "pathFromRoot": ["yu_1_2_8n0", "yu_1_2_8_3n1", "yu_1_2_8_3n4", "yu_1_4_8_3p2", "yu_1_4_8_5n2", "yu_1_6_8_5n1", "yu_1_6_8_5n2", "yu_1_6_8_7n3", "yu_1_6_8_7p2", "yu_1_8_7n0", "yu_1_8_2p2"]}, "system": ["Eq(xa_1_2, 1)", "Eq(xa_1_3, 1)", "Eq(xa_6_8, 0)", "Eq(xa_4_8, 0)", "Eq(xa_2_8, 0)", "Eq(xa_1_4, 1)", "Eq(xa_3_8, 0)", "Eq(xa_1_8, 1)", "Eq(xa_1_6, 1)", "Eq(xa_1_7, 0)", "Eq(xa_7_8, 1)", "Eq(xa_1_5, 1 - xa_5_8)"], "sumOmega": 6.0, "ni": 8, "pathFromRoot": ["yu_1_2_8n0", "yu_1_2_8_3n1", "yu_1_2_8_3n4", "yu_1_4_8_3p2", "yu_1_4_8_5n2", "yu_1_6_8_5n1", "yu_1_6_8_5n2", "yu_1_6_8_7n3", "yu_1_6_8_7p2", "yu_1_8_7n0"]}, "system": ["Eq(xa_1_2, 1)", "Eq(xa_1_3, 1)", "Eq(xa_6_8, 0)", "Eq(xa_4_8, 0)", "Eq(xa_2_8, 0)", "Eq(xa_1_4, 1)", "Eq(xa_3_8, 0)", "Eq(xa_1_8, 1)", "Eq(xa_1_6, 1)", "Eq(xa_1_7, 0)", "Eq(xa_7_8, 1)", "Eq(xa_1_5, 1 - xa_5_8)"], "sumOmega": 6.0, "ni": 8, "pathFromRoot": ["yu_1_2_8n0", "yu_1_2_8_3n1", "yu_1_2_8_3n4", "yu_1_4_8_3p2", "yu_1_4_8_5n2", "yu_1_6_8_5n1", "yu_1_6_8_5n2", "yu_1_6_8_7n3", "yu_1_6_8_7p2"]}, "rightC": {"seed": {"1": 0, "2": 1, "8": 1}, "partition": {"1": 0, "2": 1, "8": 1, "3": 1, "4": 1, "6": 1, "7": 0}, "isValid": false, "id": 789, "leftC": null, "rightC": null, "system": ["xa_1_6 + xa_1_7 + xa_6_8 - xa_7_8 - 2"], "sumOmega": 6.0, "ni": 8, "pathFromRoot": ["yu_1_2_8n0", "yu_1_2_8_3n1", "yu_1_2_8_3n4", "yu_1_4_8_3p2", "yu_1_4_8_5n2", "yu_1_6_8_5n1", "yu_1_6_8_5n2", "yu_1_6_8_7n3", "yu_1_6_8_7p2"]}, "system": ["Eq(xa_1_2, 1)", "Eq(xa_1_3, 1)", "Eq(xa_6_8, 0)", "Eq(xa_4_8, 0)", "Eq(xa_2_8, 0)", "Eq(xa_1_4, 1)", "Eq(xa_3_8, 0)", "Eq(xa_1_8, 1)", "Eq(xa_1_6, 1)", "Eq(xa_1_7, 0)", "Eq(xa_7_8, 1)", "Eq(xa_1_5, 1 - xa_5_8)"], "sumOmega": 4.0, "ni": 8, "pathFromRoot": ["yu_1_2_8n0", "yu_1_2_8_3n1", "yu_1_2_8_3n4", "yu_1_4_8_3p2", "yu_1_4_8_5n2", "yu_1_6_8_5n1", "yu_1_6_8_5n2", "yu_1_6_8_7n3"]}, "rightC": {"seed": {"1": 0, "2": 1, "8": 1}, "partition": {"1": 0, "2": 1, "8": 1, "3": 1, "4": 1, "6": 1, "7": 1}, "isValid": true, "id": 395, "leftC": null, "rightC": null, "system": ["Eq(xa_1_2, 1)", "Eq(xa_1_3, 1)", "Eq(xa_6_8, 0)", "Eq(xa_4_8, 0)", "Eq(xa_2_8, 0)", "Eq(xa_1_4, 1)", "Eq(xa_3_8, 0)", "Eq(xa_1_8, 1)", "Eq(xa_1_6, 1)", "Eq(xa_1_7, 1)", "Eq(xa_7_8, 0)", "Eq(xa_1_5, 1 - xa_5_8)", "xa_1_5 - xa_1_6 + xa_5_8 + xa_6_8 - 2"], "sumOmega": 4.0, "ni": 11, "pathFromRoot": ["yu_1_2_8n0", "yu_1_2_8_3n1", "yu_1_2_8_3n4", "yu_1_4_8_3p2", "yu_1_4_8_5n2", "yu_1_6_8_5n1", "yu_1_6_8_5n2", "yu_1_6_8_7n3"]}, "system": ["Eq(xa_1_2, 1)", "Eq(xa_1_3, 1)", "Eq(xa_6_8, 0)", "Eq(xa_4_8, 0)", "Eq(xa_2_8, 0)", "Eq(xa_1_4, 1)", "Eq(xa_3_8, 0)", "Eq(xa_1_8, 1)", "Eq(xa_1_6, 1)", "Eq(xa_1_5, 1 - xa_5_8)"], "sumOmega": 4.0, "ni": 7, "pathFromRoot": ["yu_1_2_8n0", "yu_1_2_8_3n1", "yu_1_2_8_3n4", "yu_1_4_8_3p2", "yu_1_4_8_5n2", "yu_1_6_8_5n1", "yu_1_6_8_5n2"]}, "system": ["Eq(xa_1_2, 1)", "Eq(xa_1_3, 1)", "Eq(xa_6_8, 0)", "Eq(xa_4_8, 0)", "Eq(xa_2_8, 0)", "Eq(xa_1_4, 1)", "Eq(xa_3_8, 0)", "Eq(xa_1_8, 1)", "Eq(xa_1_6, 1)", "Eq(xa_1_5, 1 - xa_5_8)"], "sumOmega": 4.0, "ni": 7, "pathFromRoot": ["yu_1_2_8n0", "yu_1_2_8_3n1", "yu_1_2_8_3n4", "yu_1_4_8_3p2", "yu_1_4_8_5n2", "yu_1_6_8_5n1"]}, "rightC": {"seed": {"1": 0, "2": 1, "8": 1}, "partition": {"1": 0, "2": 1, "8": 1, "3": 1, "4": 1, "6": 0}, "isValid": true, "id": 99, "leftC": {"seed": {"1": 0, "2": 1, "8": 1}, "partition": {"1": 0, "2": 1, "8": 1, "3": 1, "4": 1, "6": 0}, "isValid": true, "id": 198, "leftC": {"seed": {"1": 0, "2": 1, "8": 1}, "partition": {"1": 0, "2": 1, "8": 1, "3": 1, "4": 1, "6": 0, "7": 0}, "isValid": true, "id": 396, "leftC": {"seed": {"1": 0, "2": 1, "8": 1}, "partition": {"1": 0, "2": 1, "8": 1, "3": 1, "4": 1, "6": 0, "7": 0}, "isValid": false, "id": 792, "leftC": null, "rightC": null, "system": ["-xa_1_6 - xa_1_7 + xa_6_8 - xa_7_8"], "sumOmega": 4.0, "ni": 6, "pathFromRoot": ["yu_1_2_8n0", "yu_1_2_8_3n1", "yu_1_2_8_3n4", "yu_1_4_8_3p2", "yu_1_4_8_5n2", "yu_1_6_8_5n1", "yu_1_6_8_5n2", "yu_1_6_8_7n3", "yu_1_6_8_7p2"]}, "rightC": {"seed": {"1": 0, "2": 1, "8": 1}, "partition": {"1": 0, "2": 1, "8": 1, "3": 1, "4": 1, "6": 0, "7": 0}, "isValid": true, "id": 793, "leftC": {"seed": {"1": 0, "2": 1, "8": 1}, "partition": {"1": 0, "2": 1, "8": 1, "3": 1, "4": 1, "6": 0, "7": 0}, "isValid": false, "id": 1586, "leftC": null, "rightC": null, "system": ["xa_1_7 + xa_1_8 + xa_7_8 - 2"], "sumOmega": 4.0, "ni": 6, "pathFromRoot": ["yu_1_2_8n0", "yu_1_2_8_3n1", "yu_1_2_8_3n4", "yu_1_4_8_3p2", "yu_1_4_8_5n2", "yu_1_6_8_5n1", "yu_1_6_8_5n2", "yu_1_6_8_7n3", "yu_1_6_8_7p2", "yu_1_8_7n0"]}, "rightC": {"seed": {"1": 0, "2": 1, "8": 1}, "partition": {"1": 0, "2": 1, "8": 1, "3": 1, "4": 1, "6": 0, "7": 0}, "isValid": true, "id": 1587, "leftC": {"seed": {"1": 0, "2": 1, "8": 1}, "partition": {"1": 0, "2": 1, "8": 1, "3": 1, "4": 1, "6": 0, "7": 0}, "isValid": true, "id": 3174, "leftC": {"seed": {"1": 0, "2": 1, "8": 1}, "partition": {"1": 0, "2": 1, "8": 1, "3": 1, "4": 1, "6": 0, "7": 0}, "isValid": false, "id": 6348, "leftC": null, "rightC": null, "system": ["xa_1_7 + xa_1_8 + xa_2_7 - xa_2_8 - 2"], "sumOmega": 6.0, "ni": 6, "pathFromRoot": ["yu_1_2_8n0", "yu_1_2_8_3n1", "yu_1_2_8_3n4", "yu_1_4_8_3p2", "yu_1_4_8_5n2", "yu_1_6_8_5n1", "yu_1_6_8_5n2", "yu_1_6_8_7n3", "yu_1_6_8_7p2", "yu_1_8_7n0", "yu_1_8_2p2", "yu_1_8_2_7n2"]}, "rightC": {"seed": {"1": 0, "2": 1, "8": 1}, "partition": {"1": 0, "2": 1, "8": 1, "3": 1, "4": 1, "6": 0, "7": 0}, "isValid": true, "id": 6349, "leftC": {"seed": {"1": 0, "2": 1, "8": 1}, "partition": {"1": 0, "2": 1, "8": 1, "3": 1, "4": 1, "6": 0, "7": 0}, "isValid": false, "id": 12698, "leftC": null, "rightC": null, "system": ["xa_1_6 - xa_1_7 + xa_2_6 + xa_2_7 - 2"], "sumOmega": 6.0, "ni": 6, "pathFromRoot": ["yu_1_2_8n0", "yu_1_2_8_3n1", "yu_1_2_8_3n4", "yu_1_4_8_3p2", "yu_1_4_8_5n2", "yu_1_6_8_5n1", "yu_1_6_8_5n2", "yu_1_6_8_7n3", "yu_1_6_8_7p2", "yu_1_8_7n0", "yu_1_8_2p2", "yu_1_8_2_7n2", "yu_1_6_2_7n4"]}, "rightC": {"seed": {"1": 0, "2": 1, "8": 1}, "partition": {"1": 0, "2": 1, "8": 1, "3": 1, "4": 1, "6": 0, "7": 0}, "isValid": true, "id": 12699, "leftC": {"seed": {"1": 0, "2": 1, "8": 1}, "partition": {"1": 0, "2": 1, "8": 1, "3": 1, "4": 1, "6": 0, "7": 0}, "isValid": true, "id": 25398, "leftC": {"seed": {"1": 0, "2": 1, "8": 1}, "partition": {"1": 0, "2": 1, "8": 1, "3": 1, "4": 1, "6": 0, "7": 0, "5": 1}, "isValid": true, "id": 50796, "leftC": null, "rightC": null, "system": ["Eq(xa_1_2, 1)", "Eq(xa_2_7, 1)", "Eq(xa_1_3, 1)", "Eq(xa_2_6, 1)", "Eq(xa_6_8, 1)", "Eq(xa_4_8, 0)", "Eq(xa_2_8, 0)", "Eq(xa_1_4, 1)", "Eq(xa_3_8, 0)", "Eq(xa_1_8, 1)", "Eq(xa_1_6, 0)", "Eq(xa_1_7, 0)", "Eq(xa_7_8, 1)", "Eq(xa_2_5, xa_5_8)", "Eq(xa_1_5, 1 - xa_5_8)", "xa_1_4 - xa_1_5 + xa_2_4 + xa_2_5", "xa_1_4 - xa_1_5 + xa_2_4 + xa_2_5 - 2"], "sumOmega": 11.0, "ni": 10, "pathFromRoot": ["yu_1_2_8n0", "yu_1_2_8_3n1", "yu_1_2_8_3n4", "yu_1_4_8_3p2", "yu_1_4_8_5n2", "yu_1_6_8_5n1", "yu_1_6_8_5n2", "yu_1_6_8_7n3", "yu_1_6_8_7p2", "yu_1_8_7n0", "yu_1_8_2p2", "yu_1_8_2_7n2", "yu_1_6_2_7n4", "yu_1_6_2_5p1", "yu_1_4_2_5n4"]}, "rightC": {"seed": {"1": 0, "2": 1, "8": 1}, "partition": {"1": 0, "2": 1, "8": 1, "3": 1, "4": 1, "6": 0, "7": 0, "5": 0, "9": 0}, "isValid": true, "id": 50797, "leftC": null, "rightC": null, "system": ["Eq(xa_1_2, 1)", "Eq(xa_2_7, 1)", "Eq(xa_1_3, 1)", "Eq(xa_2_6, 1)", "Eq(xa_6_8, 1)", "Eq(xa_4_8, 0)", "Eq(xa_2_8, 0)", "Eq(xa_1_4, 1)", "Eq(xa_3_8, 0)", "Eq(xa_1_8, 1)", "Eq(xa_1_6, 0)", "Eq(xa_1_7, 0)", "Eq(xa_7_8, 1)", "Eq(xa_2_5, xa_5_8)", "Eq(xa_1_5, 1 - xa_5_8)", "xa_1_4 - xa_1_5 + xa_2_4 + xa_2_5 - 2"], "sumOmega": 46.5, "ni": 7, "pathFromRoot": ["yu_1_2_8n0", "yu_1_2_8_3n1", "yu_1_2_8_3n4", "yu_1_4_8_3p2", "yu_1_4_8_5n2", "yu_1_6_8_5n1", "yu_1_6_8_5n2", "yu_1_6_8_7n3", "yu_1_6_8_7p2", "yu_1_8_7n0", "yu_1_8_2p2", "yu_1_8_2_7n2", "yu_1_6_2_7n4", "yu_1_6_2_5p1", "yu_1_4_2_5n4"], "optimum": true}, "system": ["Eq(xa_1_2, 1)", "Eq(xa_2_7, 1)", "Eq(xa_1_3, 1)", "Eq(xa_2_6, 1)", "Eq(xa_6_8, 1)", "Eq(xa_4_8, 0)", "Eq(xa_2_8, 0)", "Eq(xa_1_4, 1)", "Eq(xa_3_8, 0)", "Eq(xa_1_8, 1)", "Eq(xa_1_6, 0)", "Eq(xa_1_7, 0)", "Eq(xa_7_8, 1)", "Eq(xa_2_5, xa_5_8)", "Eq(xa_1_5, 1 - xa_5_8)"], "sumOmega": 6.0, "ni": 6, "pathFromRoot": ["yu_1_2_8n0", "yu_1_2_8_3n1", "yu_1_2_8_3n4", "yu_1_4_8_3p2", "yu_1_4_8_5n2", "yu_1_6_8_5n1", "yu_1_6_8_5n2", "yu_1_6_8_7n3", "yu_1_6_8_7p2", "yu_1_8_7n0", "yu_1_8_2p2", "yu_1_8_2_7n2", "yu_1_6_2_7n4", "yu_1_6_2_5p1"]}, "rightC": null, "system": ["Eq(xa_1_2, 1)", "Eq(xa_2_7, 1)", "Eq(xa_1_3, 1)", "Eq(xa_2_6, 1)", "Eq(xa_6_8, 1)", "Eq(xa_4_8, 0)", "Eq(xa_2_8, 0)", "Eq(xa_1_4, 1)", "Eq(xa_3_8, 0)", "Eq(xa_1_8, 1)", "Eq(xa_1_6, 0)", "Eq(xa_1_7, 0)", "Eq(xa_7_8, 1)", "Eq(xa_1_5, 1 - xa_5_8)"], "sumOmega": 6.0, "ni": 6, "pathFromRoot": ["yu_1_2_8n0", "yu_1_2_8_3n1", "yu_1_2_8_3n4", "yu_1_4_8_3p2", "yu_1_4_8_5n2", "yu_1_6_8_5n1", "yu_1_6_8_5n2", "yu_1_6_8_7n3", "yu_1_6_8_7p2", "yu_1_8_7n0", "yu_1_8_2p2", "yu_1_8_2_7n2", "yu_1_6_2_7n4"]}, "system": ["Eq(xa_1_2, 1)", "Eq(xa_2_7, 1)", "Eq(xa_1_3, 1)", "Eq(xa_6_8, 1)", "Eq(xa_4_8, 0)", "Eq(xa_2_8, 0)", "Eq(xa_1_4, 1)", "Eq(xa_3_8, 0)", "Eq(xa_1_8, 1)", "Eq(xa_1_6, 0)", "Eq(xa_1_7, 0)", "Eq(xa_7_8, 1)", "Eq(xa_1_5, 1 - xa_5_8)"], "sumOmega": 6.0, "ni": 6, "pathFromRoot": ["yu_1_2_8n0", "yu_1_2_8_3n1", "yu_1_2_8_3n4", "yu_1_4_8_3p2", "yu_1_4_8_5n2", "yu_1_6_8_5n1", "yu_1_6_8_5n2", "yu_1_6_8_7n3", "yu_1_6_8_7p2", "yu_1_8_7n0", "yu_1_8_2p2", "yu_1_8_2_7n2"]}, "system": ["Eq(xa_1_2, 1)", "Eq(xa_1_3, 1)", "Eq(xa_6_8, 1)", "Eq(xa_4_8, 0)", "Eq(xa_2_8, 0)", "Eq(xa_1_4, 1)", "Eq(xa_3_8, 0)", "Eq(xa_1_8, 1)", "Eq(xa_1_6, 0)", "Eq(xa_1_7, 0)", "Eq(xa_7_8, 1)", "Eq(xa_1_5, 1 - xa_5_8)"], "sumOmega": 6.0, "ni": 6, "pathFromRoot": ["yu_1_2_8n0", "yu_1_2_8_3n1", "yu_1_2_8_3n4", "yu_1_4_8_3p2", "yu_1_4_8_5n2", "yu_1_6_8_5n1", "yu_1_6_8_5n2", "yu_1_6_8_7n3", "yu_1_6_8_7p2", "yu_1_8_7n0", "yu_1_8_2p2"]}, "rightC": null, "system": ["Eq(xa_1_2, 1)", "Eq(xa_1_3, 1)", "Eq(xa_6_8, 1)", "Eq(xa_4_8, 0)", "Eq(xa_2_8, 0)", "Eq(xa_1_4, 1)", "Eq(xa_3_8, 0)", "Eq(xa_1_8, 1)", "Eq(xa_1_6, 0)", "Eq(xa_1_7, 0)", "Eq(xa_7_8, 1)", "Eq(xa_1_5, 1 - xa_5_8)"], "sumOmega": 4.0, "ni": 6, "pathFromRoot": ["yu_1_2_8n0", "yu_1_2_8_3n1", "yu_1_2_8_3n4", "yu_1_4_8_3p2", "yu_1_4_8_5n2", "yu_1_6_8_5n1", "yu_1_6_8_5n2", "yu_1_6_8_7n3", "yu_1_6_8_7p2", "yu_1_8_7n0"]}, "system": ["Eq(xa_1_2, 1)", "Eq(xa_1_3, 1)", "Eq(xa_6_8, 1)", "Eq(xa_4_8, 0)", "Eq(xa_2_8, 0)", "Eq(xa_1_4, 1)", "Eq(xa_3_8, 0)", "Eq(xa_1_8, 1)", "Eq(xa_1_6, 0)", "Eq(xa_1_7, 0)", "Eq(xa_7_8, 1)", "Eq(xa_1_5, 1 - xa_5_8)"], "sumOmega": 4.0, "ni": 6, "pathFromRoot": ["yu_1_2_8n0", "yu_1_2_8_3n1", "yu_1_2_8_3n4", "yu_1_4_8_3p2", "yu_1_4_8_5n2", "yu_1_6_8_5n1", "yu_1_6_8_5n2", "yu_1_6_8_7n3", "yu_1_6_8_7p2"]}, "system": ["Eq(xa_1_2, 1)", "Eq(xa_1_3, 1)", "Eq(xa_6_8, 1)", "Eq(xa_4_8, 0)", "Eq(xa_2_8, 0)", "Eq(xa_1_4, 1)", "Eq(xa_3_8, 0)", "Eq(xa_1_8, 1)", "Eq(xa_1_6, 0)", "Eq(xa_1_7, 0)", "Eq(xa_7_8, 1)", "Eq(xa_1_5, 1 - xa_5_8)"], "sumOmega": 4.0, "ni": 6, "pathFromRoot": ["yu_1_2_8n0", "yu_1_2_8_3n1", "yu_1_2_8_3n4", "yu_1_4_8_3p2", "yu_1_4_8_5n2", "yu_1_6_8_5n1", "yu_1_6_8_5n2", "yu_1_6_8_7n3"]}, "rightC": null, "system": ["Eq(xa_1_2, 1)", "Eq(xa_1_3, 1)", "Eq(xa_6_8, 1)", "Eq(xa_4_8, 0)", "Eq(xa_2_8, 0)", "Eq(xa_1_4, 1)", "Eq(xa_3_8, 0)", "Eq(xa_1_8, 1)", "Eq(xa_1_6, 0)", "Eq(xa_1_5, 1 - xa_5_8)"], "sumOmega": 4.0, "ni": 5, "pathFromRoot": ["yu_1_2_8n0", "yu_1_2_8_3n1", "yu_1_2_8_3n4", "yu_1_4_8_3p2", "yu_1_4_8_5n2", "yu_1_6_8_5n1", "yu_1_6_8_5n2"]}, "rightC": null, "system": ["Eq(xa_1_2, 1)", "Eq(xa_1_3, 1)", "Eq(xa_6_8, 1)", "Eq(xa_4_8, 0)", "Eq(xa_2_8, 0)", "Eq(xa_1_4, 1)", "Eq(xa_3_8, 0)", "Eq(xa_1_8, 1)", "Eq(xa_1_6, 0)", "Eq(xa_1_5, 1 - xa_5_8)"], "sumOmega": 4.0, "ni": 5, "pathFromRoot": ["yu_1_2_8n0", "yu_1_2_8_3n1", "yu_1_2_8_3n4", "yu_1_4_8_3p2", "yu_1_4_8_5n2", "yu_1_6_8_5n1"]}, "system": ["Eq(xa_1_2, 1)", "Eq(xa_1_3, 1)", "Eq(xa_4_8, 0)", "Eq(xa_2_8, 0)", "Eq(xa_1_4, 1)", "Eq(xa_3_8, 0)", "Eq(xa_1_8, 1)", "Eq(xa_1_5, 1 - xa_5_8)"], "sumOmega": 4.0, "ni": 4, "pathFromRoot": ["yu_1_2_8n0", "yu_1_2_8_3n1", "yu_1_2_8_3n4", "yu_1_4_8_3p2", "yu_1_4_8_5n2"]}, "system": ["Eq(xa_1_2, 1)", "Eq(xa_3_8, 0)", "Eq(xa_1_8, 1)", "Eq(xa_1_3, 1)", "Eq(xa_4_8, 0)", "Eq(xa_2_8, 0)", "Eq(xa_1_4, 1)"], "sumOmega": 4.0, "ni": 4, "pathFromRoot": ["yu_1_2_8n0", "yu_1_2_8_3n1", "yu_1_2_8_3n4", "yu_1_4_8_3p2"]}, "rightC": null, "system": ["Eq(xa_1_2, 1)", "Eq(xa_3_8, 0)", "Eq(xa_1_8, 1)", "Eq(xa_1_3, 1)", "Eq(xa_2_8, 0)"], "sumOmega": 2.0, "ni": 3, "pathFromRoot": ["yu_1_2_8n0", "yu_1_2_8_3n1", "yu_1_2_8_3n4"]}, "rightC": null, "system": ["Eq(xa_1_2, 1)", "Eq(xa_1_8, 1)", "Eq(xa_2_8, 0)", "Eq(xa_1_3, 1 - xa_3_8)"], "sumOmega": 0, "ni": 1, "pathFromRoot": ["yu_1_2_8n0", "yu_1_2_8_3n1"]}, "rightC": null, "system": ["Eq(xa_1_2, 1)", "Eq(xa_1_8, 1)", "Eq(xa_2_8, 0)"], "sumOmega": 0, "ni": 1, "pathFromRoot": ["yu_1_2_8n0"]}, "ni": 1, "niMax": 8, "sumZeta": 65.5, "totalDualSum": 127.99999999999999, "system": ["Eq(xa_1_2, 1)", "Eq(xa_2_8, 0)", "Eq(xa_1_8, 1)"], "pathFromRoot": [], "sumOmega": 0}}